{
  "annotations": {
    "list": [
      {
        "builtIn": 1,
        "datasource": {
          "type": "datasource",
          "uid": "grafana"
        },
        "enable": true,
        "hide": true,
        "iconColor": "rgba(0, 211, 255, 1)",
        "name": "Annotations & Alerts",
        "target": {
          "limit": 100,
          "matchAny": false,
          "tags": [],
          "type": "dashboard"
        },
        "type": "dashboard"
      }
    ]
  },
  "editable": true,
  "fiscalYearStartMonth": 0,
  "graphTooltip": 0,
  "id": 87,
  "links": [],
  "liveNow": false,
  "panels": [
    {
      "collapsed": false,
      "datasource": {
        "type": "prometheus",
        "uid": "PBFA97CFB590B2093"
      },
      "gridPos": {
        "h": 1,
        "w": 24,
        "x": 0,
        "y": 0
      },
      "id": 4,
      "panels": [],
      "targets": [
        {
          "datasource": {
            "type": "prometheus",
            "uid": "PBFA97CFB590B2093"
          },
          "refId": "A"
        }
      ],
      "title": "Kafka Cluster",
      "type": "row"
    },
    {
      "datasource": {
        "type": "prometheus",
        "uid": "PBFA97CFB590B2093"
      },
      "description": "Number of active controllers in the cluster.",
      "fieldConfig": {
        "defaults": {
          "mappings": [
            {
              "options": {
                "match": "null",
                "result": {
                  "text": "N/A"
                }
              },
              "type": "special"
            }
          ],
          "thresholds": {
            "mode": "absolute",
            "steps": [
              {
                "color": "#299c46",
                "value": null
              },
              {
                "color": "#e5ac0e",
                "value": 2
              },
              {
                "color": "#bf1b00"
              }
            ]
          },
          "unit": "none"
        },
        "overrides": []
      },
      "gridPos": {
        "h": 4,
        "w": 4,
        "x": 0,
        "y": 1
      },
      "id": 2,
      "links": [],
      "maxDataPoints": 100,
      "options": {
        "colorMode": "value",
        "graphMode": "none",
        "justifyMode": "auto",
        "orientation": "vertical",
        "reduceOptions": {
          "calcs": [
            "lastNotNull"
          ],
          "fields": "",
          "values": false
        },
        "text": {},
        "textMode": "value_and_name"
      },
      "pluginVersion": "10.2.0",
      "targets": [
        {
          "datasource": {
            "type": "prometheus",
            "uid": "PBFA97CFB590B2093"
          },
          "exemplar": true,
          "expr": "kafka_controller_kafkacontroller_activecontrollercount{job=\"kafka-broker\",env=\"$env\"} > 0",
          "format": "time_series",
          "instant": true,
          "interval": "",
          "intervalFactor": 1,
          "legendFormat": "{{instance}}",
          "refId": "A"
        }
      ],
      "title": "Active Controllers",
      "type": "stat"
    },
    {
      "datasource": {
        "type": "prometheus",
        "uid": "PBFA97CFB590B2093"
      },
      "description": "Number of Brokers Online",
      "fieldConfig": {
        "defaults": {
          "color": {
            "mode": "thresholds"
          },
          "mappings": [
            {
              "options": {
                "match": "null",
                "result": {
                  "text": "N/A"
                }
              },
              "type": "special"
            }
          ],
          "thresholds": {
            "mode": "absolute",
            "steps": [
              {
                "color": "#d44a3a",
                "value": null
              },
              {
                "color": "rgba(237, 129, 40, 0.89)",
                "value": 0
              },
              {
                "color": "#299c46",
                "value": 2
              }
            ]
          },
          "unit": "none"
        },
        "overrides": []
      },
      "gridPos": {
        "h": 4,
        "w": 4,
        "x": 4,
        "y": 1
      },
      "id": 6,
      "links": [],
      "maxDataPoints": 100,
      "options": {
        "colorMode": "value",
        "graphMode": "none",
        "justifyMode": "auto",
        "orientation": "horizontal",
        "reduceOptions": {
          "calcs": [
            "lastNotNull"
          ],
          "fields": "",
          "values": false
        },
        "text": {},
        "textMode": "auto"
      },
      "pluginVersion": "10.2.0",
      "repeatDirection": "h",
      "targets": [
        {
          "datasource": {
            "type": "prometheus",
            "uid": "PBFA97CFB590B2093"
          },
          "exemplar": true,
          "expr": "count(kafka_server_replicamanager_leadercount{job=\"kafka-broker\",env=\"$env\"})",
          "format": "time_series",
          "instant": true,
          "interval": "",
          "intervalFactor": 1,
          "legendFormat": "",
          "refId": "A"
        }
      ],
      "title": "Brokers Online",
      "type": "stat"
    },
    {
      "datasource": {
        "type": "prometheus",
        "uid": "PBFA97CFB590B2093"
      },
      "description": "Partitions that are online",
      "fieldConfig": {
        "defaults": {
          "color": {
            "mode": "thresholds"
          },
          "mappings": [
            {
              "options": {
                "match": "null",
                "result": {
                  "text": "N/A"
                }
              },
              "type": "special"
            }
          ],
          "thresholds": {
            "mode": "absolute",
            "steps": [
              {
                "color": "#d44a3a",
                "value": null
              },
              {
                "color": "rgba(237, 129, 40, 0.89)",
                "value": 0
              },
              {
                "color": "#299c46",
                "value": 0
              }
            ]
          },
          "unit": "none"
        },
        "overrides": []
      },
      "gridPos": {
        "h": 4,
        "w": 4,
        "x": 8,
        "y": 1
      },
      "id": 8,
      "links": [],
      "maxDataPoints": 100,
      "options": {
        "colorMode": "value",
        "graphMode": "none",
        "justifyMode": "auto",
        "orientation": "horizontal",
        "reduceOptions": {
          "calcs": [
            "lastNotNull"
          ],
          "fields": "",
          "values": false
        },
        "text": {},
        "textMode": "auto"
      },
      "pluginVersion": "10.2.0",
      "targets": [
        {
          "datasource": {
            "type": "prometheus",
            "uid": "PBFA97CFB590B2093"
          },
          "exemplar": true,
          "expr": "sum(kafka_server_replicamanager_partitioncount{job=\"kafka-broker\",env=\"$env\"})",
          "format": "time_series",
          "instant": true,
          "interval": "",
          "intervalFactor": 1,
          "legendFormat": "",
          "refId": "A"
        }
      ],
      "title": "Online Partitions",
      "type": "stat"
    },
    {
      "datasource": {
        "type": "prometheus",
        "uid": "PBFA97CFB590B2093"
      },
      "description": "Number of under-replicated partitions (| ISR | < | all replicas |).",
      "fieldConfig": {
        "defaults": {
          "color": {
            "mode": "thresholds"
          },
          "mappings": [
            {
              "options": {
                "match": "null",
                "result": {
                  "text": "N/A"
                }
              },
              "type": "special"
            }
          ],
          "thresholds": {
            "mode": "absolute",
            "steps": [
              {
                "color": "#508642",
                "value": null
              },
              {
                "color": "rgba(237, 129, 40, 0.89)",
                "value": 1
              },
              {
                "color": "#bf1b00",
                "value": 5
              }
            ]
          },
          "unit": "none"
        },
        "overrides": []
      },
      "gridPos": {
        "h": 4,
        "w": 4,
        "x": 12,
        "y": 1
      },
      "id": 10,
      "links": [],
      "maxDataPoints": 100,
      "options": {
        "colorMode": "value",
        "graphMode": "none",
        "justifyMode": "auto",
        "orientation": "horizontal",
        "reduceOptions": {
          "calcs": [
            "lastNotNull"
          ],
          "fields": "",
          "values": false
        },
        "text": {},
        "textMode": "auto"
      },
      "pluginVersion": "10.2.0",
      "targets": [
        {
          "datasource": {
            "type": "prometheus",
            "uid": "PBFA97CFB590B2093"
          },
          "exemplar": true,
          "expr": "sum(kafka_server_replicamanager_underreplicatedpartitions{job=\"kafka-broker\",env=\"$env\"})",
          "format": "time_series",
          "hide": false,
          "instant": true,
          "interval": "",
          "intervalFactor": 2,
          "legendFormat": "",
          "refId": "A"
        }
      ],
      "title": "Under Replicated Partitions",
      "type": "stat"
    },
    {
      "datasource": {
        "type": "prometheus",
        "uid": "PBFA97CFB590B2093"
      },
      "description": "Number of partitions under min insync replicas.",
      "fieldConfig": {
        "defaults": {
          "color": {
            "mode": "thresholds"
          },
          "mappings": [
            {
              "options": {
                "match": "null",
                "result": {
                  "text": "N/A"
                }
              },
              "type": "special"
            }
          ],
          "thresholds": {
            "mode": "absolute",
            "steps": [
              {
                "color": "#508642",
                "value": null
              },
              {
                "color": "rgba(237, 129, 40, 0.89)",
                "value": 1
              },
              {
                "color": "#bf1b00",
                "value": 5
              }
            ]
          },
          "unit": "none"
        },
        "overrides": []
      },
      "gridPos": {
        "h": 4,
        "w": 4,
        "x": 16,
        "y": 1
      },
      "id": 12,
      "links": [],
      "maxDataPoints": 100,
      "options": {
        "colorMode": "value",
        "graphMode": "none",
        "justifyMode": "auto",
        "orientation": "horizontal",
        "reduceOptions": {
          "calcs": [
            "lastNotNull"
          ],
          "fields": "",
          "values": false
        },
        "text": {},
        "textMode": "auto"
      },
      "pluginVersion": "10.2.0",
      "targets": [
        {
          "datasource": {
            "type": "prometheus",
            "uid": "PBFA97CFB590B2093"
          },
          "exemplar": true,
          "expr": "sum(kafka_cluster_partition_underminisr{job=\"kafka-broker\",env=\"$env\"})",
          "format": "time_series",
          "hide": false,
          "instant": true,
          "interval": "",
          "intervalFactor": 2,
          "legendFormat": "",
          "refId": "A"
        }
      ],
      "title": "Under Min ISR Partitions",
      "type": "stat"
    },
    {
      "datasource": {
        "type": "prometheus",
        "uid": "PBFA97CFB590B2093"
      },
      "description": "Number of partitions that dont have an active leader and are hence not writable or readable.",
      "fieldConfig": {
        "defaults": {
          "color": {
            "mode": "thresholds"
          },
          "mappings": [
            {
              "options": {
                "match": "null",
                "result": {
                  "text": "N/A"
                }
              },
              "type": "special"
            }
          ],
          "thresholds": {
            "mode": "absolute",
            "steps": [
              {
                "color": "#508642",
                "value": null
              },
              {
                "color": "#ef843c",
                "value": 1
              },
              {
                "color": "#bf1b00",
                "value": 1
              }
            ]
          },
          "unit": "none"
        },
        "overrides": []
      },
      "gridPos": {
        "h": 4,
        "w": 4,
        "x": 20,
        "y": 1
      },
      "id": 14,
      "links": [],
      "maxDataPoints": 100,
      "options": {
        "colorMode": "value",
        "graphMode": "none",
        "justifyMode": "auto",
        "orientation": "horizontal",
        "reduceOptions": {
          "calcs": [
            "lastNotNull"
          ],
          "fields": "",
          "values": false
        },
        "text": {},
        "textMode": "auto"
      },
      "pluginVersion": "10.2.0",
      "targets": [
        {
          "datasource": {
            "type": "prometheus",
            "uid": "PBFA97CFB590B2093"
          },
          "exemplar": true,
          "expr": "sum(kafka_controller_kafkacontroller_offlinepartitionscount{job=\"kafka-broker\",env=\"$env\"})",
          "format": "time_series",
          "instant": true,
          "interval": "",
          "intervalFactor": 1,
          "legendFormat": "",
          "refId": "A"
        }
      ],
      "title": "Offline Partitions Count",
      "type": "stat"
    },
    {
      "collapsed": false,
      "datasource": {
        "type": "prometheus",
        "uid": "PBFA97CFB590B2093"
      },
      "gridPos": {
        "h": 1,
        "w": 24,
        "x": 0,
        "y": 5
      },
      "id": 26,
      "panels": [],
      "targets": [
        {
          "datasource": {
            "type": "prometheus",
            "uid": "PBFA97CFB590B2093"
          },
          "refId": "A"
        }
      ],
      "title": "Shema Registry",
      "type": "row"
    },
    {
      "datasource": {
        "type": "prometheus",
        "uid": "PBFA97CFB590B2093"
      },
      "fieldConfig": {
        "defaults": {
          "mappings": [],
          "thresholds": {
            "mode": "absolute",
            "steps": [
              {
                "color": "red",
                "value": null
              },
              {
                "color": "green",
                "value": 1
              }
            ]
          }
        },
        "overrides": []
      },
      "gridPos": {
        "h": 4,
        "w": 4,
        "x": 0,
        "y": 6
      },
      "id": 30,
      "options": {
        "colorMode": "value",
        "graphMode": "none",
        "justifyMode": "auto",
        "orientation": "auto",
        "reduceOptions": {
          "calcs": [
            "mean"
          ],
          "fields": "",
          "values": false
        },
        "text": {},
        "textMode": "auto"
      },
      "pluginVersion": "10.2.0",
      "targets": [
        {
          "datasource": {
            "type": "prometheus",
            "uid": "PBFA97CFB590B2093"
          },
          "exemplar": true,
          "expr": "count(kafka_schema_registry_registered_count{job=\"schema-registry\",env=\"$env\"})",
          "instant": true,
          "interval": "",
          "legendFormat": "",
          "refId": "A"
        }
      ],
      "title": "Schema Registry Instances",
      "type": "stat"
    },
    {
      "datasource": {
        "type": "prometheus",
        "uid": "PBFA97CFB590B2093"
      },
      "fieldConfig": {
        "defaults": {
          "mappings": [],
          "thresholds": {
            "mode": "absolute",
            "steps": [
              {
                "color": "green",
                "value": null
              }
            ]
          }
        },
        "overrides": []
      },
      "gridPos": {
        "h": 4,
        "w": 4,
        "x": 4,
        "y": 6
      },
      "id": 28,
      "options": {
        "colorMode": "value",
        "graphMode": "none",
        "justifyMode": "auto",
        "orientation": "auto",
        "reduceOptions": {
          "calcs": [
            "mean"
          ],
          "fields": "",
          "values": false
        },
        "text": {},
        "textMode": "auto"
      },
      "pluginVersion": "10.2.0",
      "targets": [
        {
          "datasource": {
            "type": "prometheus",
            "uid": "PBFA97CFB590B2093"
          },
          "exemplar": true,
          "expr": "sum(kafka_schema_registry_registered_count{job=\"schema-registry\",env=\"$env\"})",
          "instant": true,
          "interval": "",
          "legendFormat": "",
          "refId": "A"
        }
      ],
      "title": "Schemas registered",
      "type": "stat"
    },
    {
      "datasource": {
        "type": "prometheus",
        "uid": "PBFA97CFB590B2093"
      },
      "fieldConfig": {
        "defaults": {
          "mappings": [],
          "thresholds": {
            "mode": "absolute",
            "steps": [
              {
                "color": "green",
                "value": null
              }
            ]
          }
        },
        "overrides": []
      },
      "gridPos": {
        "h": 4,
        "w": 4,
        "x": 8,
        "y": 6
      },
      "id": 33,
      "options": {
        "colorMode": "value",
        "graphMode": "none",
        "justifyMode": "auto",
        "orientation": "auto",
        "reduceOptions": {
          "calcs": [
            "mean"
          ],
          "fields": "",
          "values": false
        },
        "text": {},
        "textMode": "auto"
      },
      "pluginVersion": "10.2.0",
      "targets": [
        {
          "datasource": {
            "type": "prometheus",
            "uid": "PBFA97CFB590B2093"
          },
          "exemplar": true,
          "expr": "sum(kafka_schema_registry_schemas_deleted{job=\"schema-registry\",env=\"$env\"})",
          "instant": true,
          "interval": "",
          "legendFormat": "",
          "refId": "A"
        }
      ],
      "title": "Schemas deleted",
      "type": "stat"
    },
    {
      "collapsed": false,
      "datasource": {
        "type": "prometheus",
        "uid": "PBFA97CFB590B2093"
      },
      "gridPos": {
        "h": 1,
        "w": 24,
        "x": 0,
        "y": 10
      },
      "id": 37,
      "panels": [],
      "repeat": "cluster",
      "targets": [
        {
          "datasource": {
            "type": "prometheus",
            "uid": "PBFA97CFB590B2093"
          },
          "refId": "A"
        }
      ],
      "title": "Kafka Connect ($kafka_connect_cluster_id) ",
      "type": "row"
    },
    {
      "datasource": {
        "type": "prometheus",
        "uid": "PBFA97CFB590B2093"
      },
      "fieldConfig": {
        "defaults": {
          "decimals": 0,
          "mappings": [],
          "noValue": "0",
          "thresholds": {
            "mode": "absolute",
            "steps": [
              {
                "color": "green",
                "value": null
              }
            ]
          }
        },
        "overrides": []
      },
      "gridPos": {
        "h": 4,
        "w": 4,
        "x": 0,
        "y": 11
      },
      "id": 39,
      "options": {
        "colorMode": "value",
        "graphMode": "none",
        "justifyMode": "auto",
        "orientation": "auto",
        "reduceOptions": {
          "calcs": [
            "mean"
          ],
          "fields": "",
          "values": false
        },
        "text": {},
        "textMode": "auto"
      },
      "pluginVersion": "10.2.0",
      "targets": [
        {
          "datasource": {
            "type": "prometheus",
            "uid": "PBFA97CFB590B2093"
          },
          "exemplar": true,
          "expr": "count(kafka_connect_connect_worker_metrics_connector_count{env=\"$env\",kafka_connect_cluster_id=~\"$kafka_connect_cluster_id\"})",
          "instant": true,
          "interval": "",
          "legendFormat": "",
          "refId": "A"
        }
      ],
      "title": "Connect worker instances",
      "type": "stat"
    },
    {
      "datasource": {
        "type": "prometheus",
        "uid": "PBFA97CFB590B2093"
      },
      "fieldConfig": {
        "defaults": {
          "decimals": 0,
          "mappings": [],
          "noValue": "0",
          "thresholds": {
            "mode": "absolute",
            "steps": [
              {
                "color": "green",
                "value": null
              }
            ]
          }
        },
        "overrides": []
      },
      "gridPos": {
        "h": 4,
        "w": 4,
        "x": 4,
        "y": 11
      },
      "id": 48,
      "options": {
        "colorMode": "value",
        "graphMode": "none",
        "justifyMode": "auto",
        "orientation": "auto",
        "reduceOptions": {
          "calcs": [
            "mean"
          ],
          "fields": "",
          "values": false
        },
        "text": {},
        "textMode": "auto"
      },
      "pluginVersion": "10.2.0",
      "targets": [
        {
          "datasource": {
            "type": "prometheus",
            "uid": "PBFA97CFB590B2093"
          },
          "exemplar": true,
          "expr": "sum(kafka_connect_connect_worker_metrics_connector_total_task_count{env=\"$env\",kafka_connect_cluster_id=~\"$kafka_connect_cluster_id\"})",
          "instant": true,
          "interval": "",
          "legendFormat": "",
          "refId": "A"
        }
      ],
      "title": "Tasks Total",
      "type": "stat"
    },
    {
      "datasource": {
        "type": "prometheus",
        "uid": "PBFA97CFB590B2093"
      },
      "fieldConfig": {
        "defaults": {
          "decimals": 0,
          "mappings": [],
          "noValue": "0",
          "thresholds": {
            "mode": "absolute",
            "steps": [
              {
                "color": "green",
                "value": null
              }
            ]
          }
        },
        "overrides": []
      },
      "gridPos": {
        "h": 4,
        "w": 4,
        "x": 8,
        "y": 11
      },
      "id": 41,
      "options": {
        "colorMode": "value",
        "graphMode": "none",
        "justifyMode": "auto",
        "orientation": "auto",
        "reduceOptions": {
          "calcs": [
            "mean"
          ],
          "fields": "",
          "values": false
        },
        "text": {},
        "textMode": "auto"
      },
      "pluginVersion": "10.2.0",
      "targets": [
        {
          "datasource": {
            "type": "prometheus",
            "uid": "PBFA97CFB590B2093"
          },
          "exemplar": true,
          "expr": "sum(kafka_connect_connect_worker_metrics_connector_running_task_count{env=\"$env\",kafka_connect_cluster_id=~\"$kafka_connect_cluster_id\"})",
          "instant": true,
          "interval": "",
          "legendFormat": "",
          "refId": "A"
        }
      ],
      "title": "Tasks Running",
      "type": "stat"
    },
    {
      "datasource": {
        "type": "prometheus",
        "uid": "PBFA97CFB590B2093"
      },
      "fieldConfig": {
        "defaults": {
          "decimals": 0,
          "mappings": [],
          "noValue": "0",
          "thresholds": {
            "mode": "absolute",
            "steps": [
              {
                "color": "green",
                "value": null
              },
              {
                "color": "orange",
                "value": 1
              }
            ]
          }
        },
        "overrides": []
      },
      "gridPos": {
        "h": 4,
        "w": 4,
        "x": 12,
        "y": 11
      },
      "id": 43,
      "options": {
        "colorMode": "value",
        "graphMode": "area",
        "justifyMode": "auto",
        "orientation": "auto",
        "reduceOptions": {
          "calcs": [
            "mean"
          ],
          "fields": "",
          "values": false
        },
        "text": {},
        "textMode": "auto"
      },
      "pluginVersion": "10.2.0",
      "targets": [
        {
          "datasource": {
            "type": "prometheus",
            "uid": "PBFA97CFB590B2093"
          },
          "expr": "sum(kafka_connect_connect_worker_metrics_connector_paused_task_count{env=\"$env\",instance=~\"$instance\",kafka_connect_cluster_id=~\"$kafka_connect_cluster_id\",connector=~\"$connector\"})",
          "instant": true,
          "interval": "",
          "legendFormat": "",
          "refId": "A"
        }
      ],
      "title": "Tasks Paused",
      "transformations": [],
      "type": "stat"
    },
    {
      "datasource": {
        "type": "prometheus",
        "uid": "PBFA97CFB590B2093"
      },
      "fieldConfig": {
        "defaults": {
          "decimals": 0,
          "mappings": [],
          "noValue": "0",
          "thresholds": {
            "mode": "absolute",
            "steps": [
              {
                "color": "green",
                "value": null
              },
              {
                "color": "red",
                "value": 1
              }
            ]
          }
        },
        "overrides": []
      },
      "gridPos": {
        "h": 4,
        "w": 4,
        "x": 16,
        "y": 11
      },
      "id": 45,
      "options": {
        "colorMode": "value",
        "graphMode": "area",
        "justifyMode": "auto",
        "orientation": "auto",
        "reduceOptions": {
          "calcs": [
            "lastNotNull"
          ],
          "fields": "",
          "values": false
        },
        "text": {},
        "textMode": "auto"
      },
      "pluginVersion": "10.2.0",
      "targets": [
        {
          "datasource": {
            "type": "prometheus",
            "uid": "PBFA97CFB590B2093"
          },
          "expr": "sum(kafka_connect_connect_worker_metrics_connector_failed_task_count{env=\"$env\",instance=~\"$instance\",kafka_connect_cluster_id=~\"$kafka_connect_cluster_id\",connector=~\"$connector\"})",
          "instant": true,
          "interval": "",
          "legendFormat": "",
          "refId": "A"
        }
      ],
      "title": "Tasks Failed",
      "transformations": [],
      "type": "stat"
    },
    {
      "datasource": {
        "type": "prometheus",
        "uid": "PBFA97CFB590B2093"
      },
      "description": "Time since last rebalance",
      "fieldConfig": {
        "defaults": {
          "decimals": 0,
          "mappings": [
            {
              "options": {
                "match": "null",
                "result": {
                  "text": "N/A"
                }
              },
              "type": "special"
            }
          ],
          "thresholds": {
            "mode": "absolute",
            "steps": [
              {
                "color": "#299c46",
                "value": null
              }
            ]
          },
          "unit": "clockms"
        },
        "overrides": []
      },
      "gridPos": {
        "h": 4,
        "w": 4,
        "x": 20,
        "y": 11
      },
      "id": 47,
      "links": [],
      "maxDataPoints": 100,
      "options": {
        "colorMode": "value",
        "fieldOptions": {
          "calcs": [
            "lastNotNull"
          ]
        },
        "graphMode": "none",
        "justifyMode": "auto",
        "orientation": "horizontal",
        "reduceOptions": {
          "calcs": [
            "lastNotNull"
          ],
          "fields": "",
          "values": false
        },
        "text": {},
        "textMode": "auto"
      },
      "pluginVersion": "10.2.0",
      "repeat": "instance",
      "targets": [
        {
          "datasource": {
            "type": "prometheus",
            "uid": "PBFA97CFB590B2093"
          },
          "exemplar": true,
          "expr": "kafka_connect_connect_worker_rebalance_metrics_time_since_last_rebalance_ms{env=\"$env\",job=\"connect\",kafka_connect_cluster_id=~\"$kafka_connect_cluster_id\"} >= 0",
          "format": "time_series",
          "instant": false,
          "interval": "",
          "intervalFactor": 1,
          "legendFormat": "{{instance}}",
          "refId": "A"
        }
      ],
      "title": "Time since last rebalance ",
      "type": "stat"
    },
    {
      "collapsed": false,
      "datasource": {
        "type": "prometheus",
        "uid": "PBFA97CFB590B2093"
      },
      "gridPos": {
        "h": 1,
        "w": 24,
        "x": 0,
        "y": 15
      },
      "id": 52,
      "panels": [],
      "repeat": "clusterid",
      "targets": [
        {
          "datasource": {
            "type": "prometheus",
            "uid": "PBFA97CFB590B2093"
          },
          "refId": "A"
        }
      ],
      "title": "ksqlDB Cluster ($ksqldb_cluster_id) ",
      "type": "row"
    },
    {
      "datasource": {
        "type": "prometheus",
        "uid": "PBFA97CFB590B2093"
      },
      "description": "Average number of active queries per server.",
      "fieldConfig": {
        "defaults": {
          "mappings": [
            {
              "options": {
                "match": "null",
                "result": {
                  "text": "N/A"
                }
              },
              "type": "special"
            }
          ],
          "thresholds": {
            "mode": "absolute",
            "steps": [
              {
                "color": "#d44a3a",
                "value": null
              },
              {
                "color": "rgba(237, 129, 40, 0.89)",
                "value": 0
              },
              {
                "color": "#299c46",
                "value": 1
              }
            ]
          },
          "unit": "none"
        },
        "overrides": []
      },
      "gridPos": {
        "h": 4,
        "w": 4,
        "x": 0,
        "y": 16
      },
      "id": 50,
      "links": [],
      "maxDataPoints": 100,
      "options": {
        "colorMode": "value",
        "graphMode": "none",
        "justifyMode": "auto",
        "orientation": "horizontal",
        "reduceOptions": {
          "calcs": [
            "lastNotNull"
          ],
          "fields": "",
          "values": false
        },
        "text": {},
        "textMode": "auto"
      },
      "pluginVersion": "10.2.0",
      "targets": [
        {
          "datasource": {
            "type": "prometheus",
            "uid": "PBFA97CFB590B2093"
          },
          "exemplar": true,
          "expr": "count(ksql_ksql_engine_query_stats_num_active_queries{job=\"ksqldb\", env=\"$env\", ksql_cluster=\"$ksqldb_cluster_id\"})",
          "instant": true,
          "interval": "",
          "legendFormat": "",
          "refId": "A"
        }
      ],
      "title": "ksqlDB instances",
      "type": "stat"
    },
    {
      "datasource": {
        "type": "prometheus",
        "uid": "PBFA97CFB590B2093"
      },
      "description": "Average number of active queries per server.",
      "fieldConfig": {
        "defaults": {
          "mappings": [
            {
              "options": {
                "match": "null",
                "result": {
                  "text": "N/A"
                }
              },
              "type": "special"
            }
          ],
          "thresholds": {
            "mode": "absolute",
            "steps": [
              {
                "color": "#d44a3a",
                "value": null
              },
              {
                "color": "rgba(237, 129, 40, 0.89)",
                "value": 0
              },
              {
                "color": "#299c46",
                "value": 1
              }
            ]
          },
          "unit": "none"
        },
        "overrides": []
      },
      "gridPos": {
        "h": 4,
        "w": 4,
        "x": 4,
        "y": 16
      },
      "id": 53,
      "links": [],
      "maxDataPoints": 100,
      "options": {
        "colorMode": "value",
        "graphMode": "none",
        "justifyMode": "auto",
        "orientation": "horizontal",
        "reduceOptions": {
          "calcs": [
            "lastNotNull"
          ],
          "fields": "",
          "values": false
        },
        "text": {},
        "textMode": "auto"
      },
      "pluginVersion": "10.2.0",
      "targets": [
        {
          "datasource": {
            "type": "prometheus",
            "uid": "PBFA97CFB590B2093"
          },
          "exemplar": true,
          "expr": "avg(ksql_ksql_engine_query_stats_num_active_queries{job=\"ksqldb\", env=\"$env\", ksql_cluster=\"$ksqldb_cluster_id\"})",
          "instant": true,
          "interval": "",
          "legendFormat": "",
          "refId": "A"
        }
      ],
      "title": "Active Queries",
      "type": "stat"
    },
    {
      "datasource": {
        "type": "prometheus",
        "uid": "PBFA97CFB590B2093"
      },
      "description": "Num of created queries",
      "fieldConfig": {
        "defaults": {
          "mappings": [
            {
              "options": {
                "match": "null",
                "result": {
                  "text": "N/A"
                }
              },
              "type": "special"
            }
          ],
          "thresholds": {
            "mode": "absolute",
            "steps": [
              {
                "color": "#299c46",
                "value": null
              },
              {
                "color": "rgba(237, 129, 40, 0.89)",
                "value": 500
              },
              {
                "color": "#d44a3a",
                "value": 800
              }
            ]
          },
          "unit": "none"
        },
        "overrides": []
      },
      "gridPos": {
        "h": 4,
        "w": 4,
        "x": 8,
        "y": 16
      },
      "id": 55,
      "links": [],
      "maxDataPoints": 100,
      "options": {
        "colorMode": "value",
        "graphMode": "none",
        "justifyMode": "auto",
        "orientation": "horizontal",
        "reduceOptions": {
          "calcs": [
            "lastNotNull"
          ],
          "fields": "",
          "values": false
        },
        "text": {},
        "textMode": "auto"
      },
      "pluginVersion": "10.2.0",
      "targets": [
        {
          "datasource": {
            "type": "prometheus",
            "uid": "PBFA97CFB590B2093"
          },
          "exemplar": true,
          "expr": "avg(ksql_ksql_engine_query_stats_running_queries{job=\"ksqldb\", env=\"$env\", ksql_cluster=\"$ksqldb_cluster_id\"})",
          "interval": "",
          "legendFormat": "",
          "refId": "A"
        }
      ],
      "title": "Running Queries",
      "type": "stat"
    },
    {
      "datasource": {
        "type": "prometheus",
        "uid": "PBFA97CFB590B2093"
      },
      "description": "Num of rebalancing queries",
      "fieldConfig": {
        "defaults": {
          "mappings": [
            {
              "options": {
                "match": "null",
                "result": {
                  "text": "N/A"
                }
              },
              "type": "special"
            }
          ],
          "thresholds": {
            "mode": "absolute",
            "steps": [
              {
                "color": "#299c46",
                "value": null
              },
              {
                "color": "rgba(237, 129, 40, 0.89)",
                "value": 1
              },
              {
                "color": "#d44a3a",
                "value": 5
              }
            ]
          },
          "unit": "none"
        },
        "overrides": []
      },
      "gridPos": {
        "h": 4,
        "w": 4,
        "x": 12,
        "y": 16
      },
      "id": 57,
      "links": [],
      "maxDataPoints": 100,
      "options": {
        "colorMode": "value",
        "graphMode": "none",
        "justifyMode": "auto",
        "orientation": "horizontal",
        "reduceOptions": {
          "calcs": [
            "lastNotNull"
          ],
          "fields": "",
          "values": false
        },
        "text": {},
        "textMode": "auto"
      },
      "pluginVersion": "10.2.0",
      "targets": [
        {
          "datasource": {
            "type": "prometheus",
            "uid": "PBFA97CFB590B2093"
          },
          "exemplar": true,
          "expr": "sum(ksql_ksql_engine_query_stats_rebalancing_queries{job=\"ksqldb\", env=\"$env\", ksql_cluster=\"$ksqldb_cluster_id\"})",
          "interval": "",
          "legendFormat": "",
          "refId": "A"
        }
      ],
      "title": "Rebalancing Queries",
      "type": "stat"
    },
    {
      "datasource": {
        "type": "prometheus",
        "uid": "PBFA97CFB590B2093"
      },
      "description": "Number of error query",
      "fieldConfig": {
        "defaults": {
          "mappings": [
            {
              "options": {
                "match": "null",
                "result": {
                  "text": "N/A"
                }
              },
              "type": "special"
            }
          ],
          "thresholds": {
            "mode": "absolute",
            "steps": [
              {
                "color": "#299c46",
                "value": null
              },
              {
                "color": "rgba(237, 129, 40, 0.89)",
                "value": 1
              },
              {
                "color": "#d44a3a",
                "value": 2
              }
            ]
          },
          "unit": "none"
        },
        "overrides": []
      },
      "gridPos": {
        "h": 4,
        "w": 4,
        "x": 16,
        "y": 16
      },
      "id": 59,
      "links": [],
      "maxDataPoints": 100,
      "options": {
        "colorMode": "value",
        "graphMode": "none",
        "justifyMode": "auto",
        "orientation": "horizontal",
        "reduceOptions": {
          "calcs": [
            "lastNotNull"
          ],
          "fields": "",
          "values": false
        },
        "text": {},
        "textMode": "auto"
      },
      "pluginVersion": "10.2.0",
      "targets": [
        {
          "datasource": {
            "type": "prometheus",
            "uid": "PBFA97CFB590B2093"
          },
          "exemplar": true,
          "expr": "avg(ksql_ksql_engine_query_stats_error_queries{job=\"ksqldb\", env=\"$env\", ksql_cluster=\"$ksqldb_cluster_id\"})",
          "interval": "",
          "legendFormat": "",
          "refId": "A"
        }
      ],
      "title": "Queries in Error State",
      "type": "stat"
    },
    {
      "datasource": {
        "type": "prometheus",
        "uid": "PBFA97CFB590B2093"
      },
      "description": "Num of not running queries",
      "fieldConfig": {
        "defaults": {
          "mappings": [
            {
              "options": {
                "match": "null",
                "result": {
                  "text": "N/A"
                }
              },
              "type": "special"
            }
          ],
          "thresholds": {
            "mode": "absolute",
            "steps": [
              {
                "color": "#299c46",
                "value": null
              },
              {
                "color": "rgba(237, 129, 40, 0.89)",
                "value": 1
              },
              {
                "color": "#d44a3a",
                "value": 5
              }
            ]
          },
          "unit": "none"
        },
        "overrides": []
      },
      "gridPos": {
        "h": 4,
        "w": 4,
        "x": 20,
        "y": 16
      },
      "id": 61,
      "links": [],
      "maxDataPoints": 100,
      "options": {
        "colorMode": "value",
        "graphMode": "none",
        "justifyMode": "auto",
        "orientation": "horizontal",
        "reduceOptions": {
          "calcs": [
            "lastNotNull"
          ],
          "fields": "",
          "values": false
        },
        "text": {},
        "textMode": "auto"
      },
      "pluginVersion": "10.2.0",
      "targets": [
        {
          "datasource": {
            "type": "prometheus",
            "uid": "PBFA97CFB590B2093"
          },
          "exemplar": true,
          "expr": "sum(ksql_ksql_engine_query_stats_not_running_queries{job=\"ksqldb\", env=\"$env\", ksql_cluster=\"$ksqldb_cluster_id\"})",
          "interval": "",
          "legendFormat": "",
          "refId": "A"
        }
      ],
      "title": "Stopped Queries",
      "type": "stat"
    }
  ],
  "refresh": "",
  "schemaVersion": 38,
  "tags": [
    "kafka"
  ],
  "templating": {
    "list": [
      {
        "current": {
          "selected": false,
          "text": "dev",
          "value": "dev"
        },
        "datasource": {
          "type": "prometheus",
          "uid": "PBFA97CFB590B2093"
        },
        "definition": "label_values(env)",
        "hide": 0,
        "includeAll": false,
        "label": "Environment",
        "multi": false,
        "name": "env",
        "options": [],
        "query": {
          "query": "label_values(env)",
          "refId": "StandardVariableQuery"
        },
        "refresh": 1,
        "regex": "",
        "skipUrlSync": false,
        "sort": 0,
        "type": "query"
      },
      {
        "current": {
          "selected": false,
          "text": "cluster1",
          "value": "cluster1"
        },
        "datasource": {
          "type": "prometheus",
          "uid": "PBFA97CFB590B2093"
        },
        "definition": "label_values(kafka_connect_cluster_id)",
        "hide": 0,
        "includeAll": false,
        "label": "Kafka Connect Cluster ID",
        "multi": false,
        "name": "kafka_connect_cluster_id",
        "options": [],
        "query": {
          "query": "label_values(kafka_connect_cluster_id)",
          "refId": "StandardVariableQuery"
        },
        "refresh": 1,
        "regex": "",
        "skipUrlSync": false,
        "sort": 0,
        "type": "query"
      },
      {
        "current": {
          "selected": false,
          "text": "ksqldb-cluster",
          "value": "ksqldb-cluster"
        },
        "datasource": {
          "type": "prometheus",
          "uid": "PBFA97CFB590B2093"
        },
        "definition": "label_values(ksql_ksql_engine_query_stats_liveness_indicator,ksql_cluster)",
        "hide": 0,
        "includeAll": false,
        "label": "ksqlDB Cluster ID",
        "multi": false,
        "name": "ksqldb_cluster_id",
        "options": [],
        "query": {
          "query": "label_values(ksql_ksql_engine_query_stats_liveness_indicator,ksql_cluster)",
          "refId": "StandardVariableQuery"
        },
        "refresh": 1,
        "regex": "",
        "skipUrlSync": false,
        "sort": 0,
        "type": "query"
      }
    ]
  },
  "time": {
    "from": "now-12h",
    "to": "now"
  },
  "timepicker": {},
  "timezone": "",
  "title": "Confluent Platform overview",
  "uid": null,
  "version": 1,
  "weekStart": ""
}